sarif/__init__.py
sarif/__main__.py
sarif/charts.py
sarif/cmdline/__init__.py
sarif/cmdline/main.py
sarif/filter/__init__.py
sarif/filter/filter_stats.py
sarif/filter/general_filter.py
sarif/issues_report.py
sarif/loader.py
sarif/operations/__init__.py
sarif/operations/blame_op.py
sarif/operations/codeclimate_op.py
sarif/operations/copy_op.py
sarif/operations/csv_op.py
sarif/operations/diff_op.py
sarif/operations/emacs_op.py
sarif/operations/html_op.py
sarif/operations/info_op.py
sarif/operations/ls_op.py
sarif/operations/summary_op.py
sarif/operations/templates/sarif_emacs.txt
sarif/operations/templates/sarif_summary.html
sarif/operations/trend_op.py
sarif/operations/upgrade_filter_op.py
sarif/operations/word_op.py
sarif/sarif_file.py
sarif/sarif_file_utils.py
sarif_tools-3.0.4.dist-info/LICENSE
sarif_tools-3.0.4.dist-info/METADATA
sarif_tools-3.0.4.dist-info/WHEEL
sarif_tools-3.0.4.dist-info/entry_points.txt
sarif_tools-3.0.4.dist-info/RECORD
