Metadata-Version: 2.1
Name: sarif-tools
Version: 3.0.4
Summary: SARIF tools
Home-page: https://github.com/microsoft/sarif-tools
Author: Microsoft
Requires-Python: >=3.8,<4.0
Classifier: License :: OSI Approved :: MIT License
Classifier: Operating System :: OS Independent
Classifier: Programming Language :: Python :: 3
Classifier: Programming Language :: Python :: 3.8
Classifier: Programming Language :: Python :: 3.9
Classifier: Programming Language :: Python :: 3.10
Classifier: Programming Language :: Python :: 3.11
Classifier: Programming Language :: Python :: 3.12
Classifier: Programming Language :: Python :: 3.13
Requires-Dist: jinja2 (>=3.1.4,<4.0.0)
Requires-Dist: jsonpath-ng (>=1.6.0,<2.0.0)
Requires-Dist: matplotlib (>=3.7,<4.0)
Requires-Dist: python-docx (>=1.1.2,<2.0.0)
Requires-Dist: pyyaml (>=6.0.1,<7.0.0)
Project-URL: Bug Tracker, https://github.com/microsoft/sarif-tools/issues
